pydobe/__init__.py
pydobe/adobe_objects.py
pydobe/core.py
pydobe/utils.py
pydobe/after_effects/ae_utils.py
pydobe/after_effects/data.py
pydobe/after_effects/objects/ae_objects.py
pydobe/after_effects/objects/root.py
pydobe-0.5.0.dist-info/LICENSE
pydobe-0.5.0.dist-info/METADATA
pydobe-0.5.0.dist-info/WHEEL
pydobe-0.5.0.dist-info/top_level.txt
pydobe-0.5.0.dist-info/RECORD
