Metadata-Version: 2.1
Name: pydobe
Version: 0.5.0
Summary: Python wrapper allowing developers to communicate with adobe applications
Author-email: Lisa George-Gilroy <Lisa.gg89@gmail.com>
License: MIT License
Project-URL: Homepage, https://github.com/LisaGG89/pydobe
Keywords: python,adobe,wrapper
Classifier: License :: OSI Approved :: MIT License
Classifier: Intended Audience :: Developers
Classifier: Programming Language :: Python :: 3
Classifier: Operating System :: Microsoft :: Windows
Requires-Python: >=3.8
License-File: LICENSE
Requires-Dist: requests (>=2.28.2)
Provides-Extra: dev
Requires-Dist: black ; extra == 'dev'
Requires-Dist: PySide2 ; extra == 'dev'
